admitted/__init__.py
admitted/_base.py
admitted/_constants.py
admitted/_locator.py
admitted/_service.py
admitted/_url.py
admitted/_window.py
admitted/element.py
admitted/exceptions.py
admitted/models.py
admitted/page.py
admitted/site.py
admitted/_executables/__init__.py
admitted/_executables/_manager.py
admitted/_executables/_platform.py
admitted-2025.2.dist-info/licenses/LICENSE
admitted-2025.2.dist-info/METADATA
admitted-2025.2.dist-info/WHEEL
admitted-2025.2.dist-info/top_level.txt
admitted-2025.2.dist-info/RECORD
