Metadata-Version: 2.4
Name: admitted
Version: 2025.2
Summary: Utility to make automating processes using Selenium and Chromedriver easier
Author-email: Joe Carey <joe@accountingdatasolutions.com>
License: MIT
Project-URL: Homepage, https://git.accountingdatasolutions.com/indepndnt/admitted
Classifier: Development Status :: 3 - Alpha
Classifier: Programming Language :: Python
Classifier: Programming Language :: Python :: 3
Classifier: Programming Language :: Python :: 3.11
Classifier: Programming Language :: Python :: 3.12
Classifier: Programming Language :: Python :: 3.13
Classifier: License :: OSI Approved :: MIT License
Classifier: Operating System :: OS Independent
Requires-Python: >=3.11
License-File: LICENSE
Requires-Dist: cssselect<2.0,>=1.2.0
Requires-Dist: lxml<6.0,>=5.3.0
Requires-Dist: psutil<7.0,>=6.1.0
Requires-Dist: selenium<5.0,>=4.26.0
Requires-Dist: urllib3<3.0,>=2.0.7
Provides-Extra: debug
Requires-Dist: html2text>=2024.2.26; extra == "debug"
Provides-Extra: dev
Requires-Dist: black>24.0.0; extra == "dev"
Requires-Dist: coverage[toml]>7.6.4; extra == "dev"
Requires-Dist: html2text>=2024.2.26; extra == "dev"
Requires-Dist: pytest>=8.3.3; extra == "dev"
Requires-Dist: ruff>=0.7.1; extra == "dev"
Requires-Dist: toml>=0.10.2; extra == "dev"
Requires-Dist: lxml-stubs>=0.5.1; extra == "dev"
Dynamic: license-file
